[
    {
        "id": 1,
        "name": "Navdeep",
        "img": "https://www.upwork.com/profile-portraits/c13wrecag3zg_YqEl9aIbxmA8rRBf1vhBxEKoDtCrmBF4silJCGmhNJgWuCV--umwy",
        "designation": "FullStack Developer",
        "age": 26,
        "country": "USA",
        "salary": 222000
    },
    {
        "id": 2,
        "name": "Alex",
        "img": "https://www.upwork.com/profile-portraits/c1YehTA5QpKRvygyBVdm355IujQT7EqAuL-WpLW03cQbovpV1zVqWnI2L4SPIiDxJi",
        "designation": "FullStack Developer",
        "age": 28,
        "country": "England",
        "salary": 422000
    },
    {
        "id": 3,
        "name": "Emaliano",
        "img": "https://www.upwork.com/profile-portraits/c1wXfcrTNZ2sLlDlZHlQOINFbmdTj585hVoeg3A8vQpaIaxfIplWptlx104l5JqG0O",
        "designation": "Backend Developer",
        "age": 22,
        "country": "Norway",
        "salary": 12000
    },
    {
        "id": 4,
        "name": "john flix",
        "img": "https://www.upwork.com/profile-portraits/c1tP2bcdlouGRJKb4nQTJXszTdGZGi8xPZX17AWYKqLlPtqWJyNbDy3udJvyYumX6b",
        "designation": "Frontend Developer",
        "age": 32,
        "country": "Sweden",
        "salary": 15000
    },
    {
        "id": 5,
        "name": "Roccumnoio",
        "img": "https://www.upwork.com/profile-portraits/c1Op3WY0_QuJWQHmjBjIsJGOHQo-O3exD7PzGNz0K5ZWpqd_-VP62SllKmDFvrgmPx",
        "designation": "FullStack Developer",
        "age": 26,
        "country": "Germany",
        "salary": 240000
    },
    {
        "id": 6,
        "name": "Jackson",
        "img": "https://www.upwork.com/profile-portraits/c1q2SAgM2DpKg45tzUnHMAST71ntcpsYEOw0Opt7QTEzWHPjdNPDhEczleiafj2aSX",
        "designation": "Nodejs Developer",
        "age": 48,
        "country": "Spain",
        "salary": 18000
    },
    {
        "id": 7,
        "name": "Klopp",
        "img": "https://www.upwork.com/profile-portraits/c1GHwOf_Mnstq-klBWbEhc4wNiqNaqobzm-KzjSvcyTTRw6Frb_V_hDLoWT_IwjGxa",
        "designation": "Reactjs Developer",
        "age": 28,
        "country": "Russia",
        "salary": 222000
    },
    {
        "id": 8,
        "name": "Bonsai",
        "img": "https://www.upwork.com/profile-portraits/c1yTlfeROrIKG5W0qzhbGmr5DzjLYXX2mGyycCIJMpa6_odnblhH8qIq4iIkZaRb45",
        "designation": "FullStack Developer",
        "age": 19,
        "country": "USA",
        "salary": 222000
    },
    {
        "id": 9,
        "name": "Richarsan",
        "img": "https://www.upwork.com/profile-portraits/c17BjE1sakcyc9bs6W4rksnHrCgSVnWwvh3ndQ1QZIk20ZR9FF6JlG9xigl-GyA5VL",
        "designation": "Nodejs Developer",
        "age": 32,
        "country": "England",
        "salary": 210000
    },
    {
        "id": 10,
        "name": "Mohaimilun",
        "img": "https://www.upwork.com/profile-portraits/c111hHb1K6Dok4ZG0W5CrJzcf5j2Ig-r1l9xHGQk5gQjiJ6JeV2gYKEOWvxJwObvI9",
        "designation": "FullStack Developer",
        "age": 33,
        "country": "Pakistan",
        "salary": 182000
    },
    {
        "id": 11,
        "name": "Nikkson",
        "img": "https://www.upwork.com/profile-portraits/c1mJx-90w0C9QoYeO_4e2vMCad5HqtrwnHgxNKHCGiV3h5kVsLxlr6f_51RA_8xPI2",
        "designation": "Frontend Developer",
        "age": 16,
        "country": "Nepal",
        "salary": 160000
    },
    {
        "id": 12,
        "name": "Rasid",
        "img": "https://www.upwork.com/profile-portraits/c1N2BZgfNGMbh3o3NJsM_QwJw26o19zdLe_Yih6OYGQf4-mIBknZZvbPCOEw6lwNGs",
        "designation": "FullStack Developer",
        "age": 25,
        "country": "Pakistan",
        "salary": 170000
    }
]